{
  "tableName": "Controls",
  "rowCount": 47,
  "columns": [
    {
      "name": "ID",
      "type": "INTEGER",
      "notNull": false,
      "defaultValue": null,
      "primaryKey": true,
      "position": 0
    },
    {
      "name": "Type",
      "type": "TEXT",
      "notNull": true,
      "defaultValue": null,
      "primaryKey": false,
      "position": 1
    },
    {
      "name": "Description",
      "type": "TEXT",
      "notNull": false,
      "defaultValue": null,
      "primaryKey": false,
      "position": 2
    },
    {
      "name": "Help",
      "type": "TEXT",
      "notNull": false,
      "defaultValue": null,
      "primaryKey": false,
      "position": 3
    },
    {
      "name": "DisabledHelp",
      "type": "TEXT",
      "notNull": false,
      "defaultValue": null,
      "primaryKey": false,
      "position": 4
    },
    {
      "name": "Button",
      "type": "TEXT",
      "notNull": false,
      "defaultValue": null,
      "primaryKey": false,
      "position": 5
    },
    {
      "name": "HotKey",
      "type": "TEXT",
      "notNull": false,
      "defaultValue": null,
      "primaryKey": false,
      "position": 6
    },
    {
      "name": "HotKeyAlt",
      "type": "TEXT",
      "notNull": false,
      "defaultValue": null,
      "primaryKey": false,
      "position": 7
    },
    {
      "name": "HotKeyPriority",
      "type": "INTEGER",
      "notNull": false,
      "defaultValue": "0",
      "primaryKey": false,
      "position": 8
    },
    {
      "name": "HotKeyPriorityAlt",
      "type": "INTEGER",
      "notNull": false,
      "defaultValue": "0",
      "primaryKey": false,
      "position": 9
    },
    {
      "name": "AltDown",
      "type": "boolean",
      "notNull": false,
      "defaultValue": "0",
      "primaryKey": false,
      "position": 10
    },
    {
      "name": "AltDownAlt",
      "type": "boolean",
      "notNull": false,
      "defaultValue": "0",
      "primaryKey": false,
      "position": 11
    },
    {
      "name": "ShiftDown",
      "type": "boolean",
      "notNull": false,
      "defaultValue": "0",
      "primaryKey": false,
      "position": 12
    },
    {
      "name": "ShiftDownAlt",
      "type": "boolean",
      "notNull": false,
      "defaultValue": "0",
      "primaryKey": false,
      "position": 13
    },
    {
      "name": "CtrlDown",
      "type": "boolean",
      "notNull": false,
      "defaultValue": "0",
      "primaryKey": false,
      "position": 14
    },
    {
      "name": "CtrlDownAlt",
      "type": "boolean",
      "notNull": false,
      "defaultValue": "0",
      "primaryKey": false,
      "position": 15
    }
  ],
  "primaryKeys": [
    "ID"
  ],
  "foreignKeys": [],
  "indexes": [
    {
      "name": "sqlite_autoindex_Controls_1",
      "unique": true,
      "partial": false
    }
  ],
  "createStatement": "CREATE TABLE Controls ('ID' integer primary key autoincrement , 'Type' text  not null unique , 'Description' text , 'Help' text , 'DisabledHelp' text , 'Button' text , 'HotKey' text , 'HotKeyAlt' text , 'HotKeyPriority' integer default 0 , 'HotKeyPriorityAlt' integer default 0 , 'AltDown' boolean default 0 , 'AltDownAlt' boolean default 0 , 'ShiftDown' boolean default 0 , 'ShiftDownAlt' boolean default 0 , 'CtrlDown' boolean default 0 , 'CtrlDownAlt' boolean default 0 )",
  "metadata": {
    "exportDate": "2025-09-01T02:32:23.157Z"
  }
}