{
  "eventName": "TileImprovementChanged",
  "generatedAt": "2025-09-02T16:43:10.305Z",
  "occurrences": 2,
  "references": [
    {
      "file": "CvGameCoreDLL_Expansion2/CvPlot.cpp",
      "line": 8860,
      "content": "GAMEEVENTINVOKE_HOOK(GAMEEVENT_TileImprovementChanged, getX(), getY(), getOwner(), eOldImprovement, eNewValue, IsImprovementPillaged());",
      "eventName": "TileImprovementChanged",
      "args": [
        "getX()",
        "getY()",
        "getOwner()",
        "eOldImprovement",
        "eNewValue",
        "IsImprovementPillaged()"
      ]
    },
    {
      "file": "CvGameCoreDLL_Expansion2/CvPlot.cpp",
      "line": 9099,
      "content": "GAMEEVENTINVOKE_HOOK(GAMEEVENT_TileImprovementChanged, getX(), getY(), getOwner(), getImprovementType(), getImprovementType(), IsImprovementPillaged());",
      "eventName": "TileImprovementChanged",
      "args": [
        "getX()",
        "getY()",
        "getOwner()",
        "getImprovementType()",
        "getImprovementType()",
        "IsImprovementPillaged()"
      ]
    }
  ]
}